.gitignore
LICENCE.txt
README.rst
pytest_polarion_cfme.py
setup.py
pytest_polarion_cfme.egg-info/PKG-INFO
pytest_polarion_cfme.egg-info/SOURCES.txt
pytest_polarion_cfme.egg-info/dependency_links.txt
pytest_polarion_cfme.egg-info/entry_points.txt
pytest_polarion_cfme.egg-info/requires.txt
pytest_polarion_cfme.egg-info/top_level.txt