Metadata-Version: 1.1
Name: pytest-polarion-cfme
Version: 0.1.5
Summary: pytest plugin for collecting test cases and recording test results
Home-page: https://github.com/mkoura/pytest-polarion-cfme
Author: Martin Kourim
Author-email: mkourim@redhat.com
License: GPL
Keywords: polarion,py.test,pytest,testing
Platform: UNKNOWN
Classifier: Development Status :: 3 - Alpha
Classifier: Framework :: Pytest
Classifier: Topic :: Software Development :: Testing
Classifier: License :: OSI Approved :: GNU General Public License v2 (GPLv2)
Classifier: Programming Language :: Python :: 2.7
Classifier: Programming Language :: Python :: 3.3
Classifier: Programming Language :: Python :: 3.4
Classifier: Programming Language :: Python :: 3.5
Classifier: Intended Audience :: Developers
